LICENSE
MANIFEST.in
README.rst
setup.cfg
setup.py
./pandoc_img_glob/pandoc-img-glob.py
pandoc_img_glob/__init__.py
pandoc_img_glob/pandoc-img-glob.py
pandoc_img_glob/pandoc_img_glob.py
pandoc_img_glob.egg-info/PKG-INFO
pandoc_img_glob.egg-info/SOURCES.txt
pandoc_img_glob.egg-info/dependency_links.txt
pandoc_img_glob.egg-info/entry_points.txt
pandoc_img_glob.egg-info/requires.txt
pandoc_img_glob.egg-info/top_level.txt