Metadata-Version: 1.1
Name: pandoc-img-glob
Version: 0.1.3
Summary: A pandoc filter for globbing image paths in multi file projects.
Home-page: https://github.com/shoeffner/pandoc-img-glob
Author: Sebastian Höffner
Author-email: info@sebastian-hoeffner.de
License: MIT
Download-URL: https://github.com/shoeffner/pandoc-img-glob/tarball/0.1.3
Keywords: pandoc,image,multifile,filter
Platform: UNKNOWN
Classifier: Development Status :: 3 - Alpha
Classifier: Intended Audience :: Science/Research
Classifier: License :: OSI Approved :: MIT License
Classifier: Natural Language :: English
Classifier: Programming Language :: Python :: 3.6
Classifier: Topic :: Text Processing :: Filters
